plugbear/__init__.py
plugbear/fastapi.py
plugbear/py.typed
plugbear-0.1.0.dist-info/WHEEL
plugbear-0.1.0.dist-info/METADATA
plugbear-0.1.0.dist-info/RECORD
