Metadata-Version: 2.1
Name: plugbear
Version: 0.1.0
Summary: Plugbear easily integrates LLM into various channels.
Author-email: Runbear <dev@runbear.io>
Requires-Python: >=3.9
Classifier: Development Status :: 4 - Beta
Classifier: Intended Audience :: Developers
Classifier: Operating System :: OS Independent
Classifier: Programming Language :: Python :: 3
Classifier: Programming Language :: Python :: 3 :: Only
Classifier: Programming Language :: Python :: 3.9
Classifier: Programming Language :: Python :: 3.10
Classifier: Programming Language :: Python :: 3.11
Classifier: Programming Language :: Python :: 3.12
Classifier: Programming Language :: Python :: 3.13
Classifier: Typing :: Typed
Requires-Dist: aiohttp>=0.16.0
Requires-Dist: plugbear[test] ; extra == "dev"
Requires-Dist: plugbear[lint] ; extra == "dev"
Requires-Dist: plugbear[fastapi] ; extra == "dev"
Requires-Dist: fastapi>=0.51.0 ; extra == "fastapi"
Requires-Dist: ruff~=0.1 ; extra == "lint"
Requires-Dist: mypy~=1.7 ; extra == "lint"
Requires-Dist: pytest~=7.4 ; extra == "test"
Requires-Dist: pytest-asyncio~=0.23 ; extra == "test"
Requires-Dist: httpx ; extra == "test"
Project-URL: Home, https://plugbear.io/
Project-URL: Source, https://github.com/runbear-io/plugbear-python-sdk
Provides-Extra: dev
Provides-Extra: fastapi
Provides-Extra: lint
Provides-Extra: test
